{
  "project_name": "injury-prevention",
  "knode_idx": 1,
  "node_title": "工伤事故类型与发生机理",
  "user_overrides": {
    "skip_steps": [
      "0.5",
      "0.7"
    ],
    "reason": "用户明确要求本次不要执行 0.5 / 0.7。"
  },
  "style_selection": {
    "selected_style_key": "mech",
    "reason": "本节点讲的是工业现场事故分类、机械与车辆等设备相关伤害机理，以及班组级事故复盘方法，最接近 theme_style 中的 mech 工业机库语义。"
  },
  "media_considerations": [
    {
      "mode": "theory",
      "decision": "keep",
      "reason": "需要给事故分类、能量伤害、多重防线和四要素模型提供底层理解。"
    },
    {
      "mode": "animation",
      "decision": "keep",
      "reason": "适合把“20类全景 -> 边界区分 -> 四要素 -> 防线穿透”的递进过程动态讲清。"
    },
    {
      "mode": "game",
      "decision": "keep",
      "reason": "hands_on 要求学生对典型事故做四要素分解，做成事故拆解台比选择题更贴近真实复盘。"
    },
    {
      "mode": "diagram",
      "decision": "keep",
      "reason": "20 类标准名称是静态分类地图，示意图比动画更适合长期对照和速查。"
    },
    {
      "mode": "image",
      "decision": "reject",
      "reason": "单张真实照片会过度偏向某一事故类型，削弱本节覆盖 20 类全景的目标。"
    },
    {
      "mode": "hands_on_kit",
      "decision": "reject",
      "reason": "本节 hands_on 是事故数据重分类与四要素拆因，不依赖实体元器件采购。"
    },
    {
      "mode": "youtube",
      "decision": "skip_by_user",
      "reason": "按用户要求跳过 0.5。"
    },
    {
      "mode": "labxchange",
      "decision": "skip_by_user",
      "reason": "按用户要求跳过 0.7。"
    }
  ],
  "animation_divergence": [
    {
      "pattern": "分类地图 + 逐帧放大",
      "pitch": "先给出 20 类事故总图，再挑出几个最易混淆的类别放大对比，最后落到四要素与阻断点。",
      "why_cool": "兼顾全景与边界，不会把学习体验变成死背名词。"
    },
    {
      "pattern": "单案例时间线",
      "pitch": "只讲一条事故从开工到伤害发生的全过程，逐帧显示漏洞叠加。",
      "why_cool": "叙事清楚，但覆盖面太窄，不足以承担 20 类分类总览。"
    },
    {
      "pattern": "参数扫描面板",
      "pitch": "用一个事故风险控制台同时扫过能量、环境和管理变量。",
      "why_cool": "更理工，但对 foundation 节点过于抽象，容易压过标准分类主线。"
    }
  ],
  "animation_choice": {
    "selected": "分类地图 + 逐帧放大",
    "reject_others": "本节必须兼顾 20 类法定口径和发生机理，单案例过窄，纯参数扫描又太抽象。"
  },
  "game_divergence": [
    {
      "pattern": "Pattern 5 Detective / Diagnosis",
      "pitch": "玩家面对事故案例，把证据拖进人机环管四个证据仓，再启动事故链，观察危险如何穿透防线。",
      "why_cool": "直接对应 hands_on 的事故拆因动作，而且有可视化反馈，不是做题换皮。"
    },
    {
      "pattern": "Pattern 7 Strategy Map / Path Planning",
      "pitch": "玩家在事故高发岗位地图上布置整改资源，压低不同类别事故频率。",
      "why_cool": "更像管理模拟，但离本节“先会分类型、会拆因”这个 foundation 目标稍远。"
    },
    {
      "pattern": "Pattern X Classification / Matching",
      "pitch": "把事故名称拖进正确类别桶里。",
      "why_cool": "好上手，但过于像选择题，不足以满足 5.5e 对游戏性的要求。"
    }
  ],
  "game_choice": {
    "selected": "Pattern 5 Detective / Diagnosis",
    "reject_others": "策略地图偏后续模块；纯分类桶玩法过于接近考试，不满足真实交互标准。"
  },
  "creativity_gate": {
    "subtract_test": "如果去掉“运行事故链”这一步，游戏就退化成证据分类；说明这个动态反馈是核心元素。",
    "replay_test": "四个案例的证据顺序会打乱，玩家能反复练习不同类型事故的拆因顺序。",
    "surprise_test": "运行后危险束是否被阻断不是只看单张卡片，而是看四类证据是否形成完整链条，结果有涌现感。",
    "aha_test": "玩家会记住：事故不是‘某个人一下犯错’，而是四层漏洞连成了线。"
  },
  "debate": {
    "game_is_not_quiz": "核心交互是拖放证据、构建因果链、触发动态反馈，不是点选 ABCD。",
    "acceptance_alignment": "动画承接 20 类全景，游戏承接四要素完整分解，exercise 承接标准口径和速查卡验收要求。",
    "final_keep": [
      "theory",
      "animation",
      "game",
      "diagram",
      "exercise"
    ],
    "final_reject": [
      "image",
      "hands_on_kit",
      "youtube",
      "labxchange"
    ]
  }
}
